vider/__init__.py
vider/gox.py
vider_dl-0.0.1.dist-info/LICENSE
vider_dl-0.0.1.dist-info/METADATA
vider_dl-0.0.1.dist-info/WHEEL
vider_dl-0.0.1.dist-info/entry_points.txt
vider_dl-0.0.1.dist-info/top_level.txt
vider_dl-0.0.1.dist-info/RECORD
