Metadata-Version: 2.1
Name: vider-dl
Version: 0.0.1
Summary: vider.info downloader
Author-email: Dwa Bece <pypispam@c40.pl>
Project-URL: Homepage, https://github.com/dwabece/vider-dl
Project-URL: Issues, https://github.com/dwabece/vider-dl/issues
Classifier: Programming Language :: Python :: 3
Classifier: License :: OSI Approved :: MIT License
Classifier: Operating System :: OS Independent
Requires-Python: >=3.8
License-File: LICENSE
Requires-Dist: aiofiles >=24.1.0
Requires-Dist: aiohttp >=3.9.5
Requires-Dist: click >=8.1.7
Requires-Dist: tqdm >=4.66.4
Requires-Dist: beautifulsoup4 >=4.12.3
Requires-Dist: bs4 >=0.0.2
Provides-Extra: dev
Requires-Dist: ipdb ; extra == 'dev'
Requires-Dist: pytest ; extra == 'dev'
Requires-Dist: aioresponses ; extra == 'dev'
Requires-Dist: pytest-asyncio ; extra == 'dev'
Requires-Dist: pytest-mock ; extra == 'dev'
